pydebugger/__init__.py
pydebugger/__main__.py
pydebugger/__version__.py
pydebugger/cleaner.py
pydebugger/config.py
pydebugger/config1.py
pydebugger/configset.py
pydebugger/custom_rich_help_formatter.py
pydebugger/debug.ini
pydebugger/debug.py
pydebugger/debug_test.py
pydebugger/extended.py
pydebugger/test.py
pydebugger/test_cleaner.py
pydebugger-0.86.data/data/LICENSE.md
pydebugger-0.86.data/data/README.md
pydebugger-0.86.data/data/__version__.py
pydebugger-0.86.dist-info/licenses/LICENSE.md
pydebugger-0.86.dist-info/METADATA
pydebugger-0.86.dist-info/WHEEL
pydebugger-0.86.dist-info/entry_points.txt
pydebugger-0.86.dist-info/top_level.txt
pydebugger-0.86.dist-info/RECORD
