Metadata-Version: 2.4
Name: pydebugger
Version: 0.86
Summary: Print objects with inspection details and color.
Home-page: https://github.com/cumulus13/pydebugger
Author: Hadi Cahyadi LD
Author-email: cumulus13@gmail.com
Maintainer: cumulus13 Team
Maintainer-email: cumulus13@gmail.com
License: BSD
Project-URL: Documentation, https://github.com/cumulus13/pydebugger
Project-URL: Code, https://github.com/cumulus13/pydebugger
Classifier: Development Status :: 5 - Production/Stable
Classifier: Intended Audience :: Developers
Classifier: License :: OSI Approved :: BSD License
Classifier: Operating System :: OS Independent
Classifier: Programming Language :: Python
Classifier: Programming Language :: Python :: 2.7
Classifier: Programming Language :: Python :: 3
Requires-Python: >=2.7
License-File: LICENSE.md
Requires-Dist: make_colors>=3.12
Requires-Dist: configset
Requires-Dist: cmdw
Requires-Dist: configparser
Requires-Dist: sqlalchemy
Requires-Dist: rich
Requires-Dist: licface
Dynamic: author
Dynamic: author-email
Dynamic: classifier
Dynamic: description
Dynamic: description-content-type
Dynamic: home-page
Dynamic: license
Dynamic: license-file
Dynamic: maintainer
Dynamic: maintainer-email
Dynamic: project-url
Dynamic: requires-dist
Dynamic: requires-python
Dynamic: summary
